moncode/__init__.py
moncode/styles.py
moncode-0.0.2.dist-info/METADATA
moncode-0.0.2.dist-info/WHEEL
moncode-0.0.2.dist-info/entry_points.txt
moncode-0.0.2.dist-info/top_level.txt
moncode-0.0.2.dist-info/RECORD
