Metadata-Version: 2.1
Name: moncode
Version: 0.0.2
Summary: Take code from the clipboard and format it for MongoDB slides.
Home-page: https://github.com/judy2k/moncode
Author: Mark Smith
Author-email: judy@judy.co.uk
License: UNKNOWN
Keywords: tui,console,syntax,formatting,rtf,presentation,code
Platform: UNKNOWN
Classifier: Development Status :: 4 - Beta
Classifier: Programming Language :: Python :: 3
Classifier: Programming Language :: Python :: 3.6
Classifier: Programming Language :: Python :: 3.7
Classifier: Programming Language :: Python :: 3.8
Classifier: License :: OSI Approved :: Apache Software License
Classifier: Environment :: Console
Classifier: Operating System :: OS Independent
Requires-Dist: click (~=7.1)
Requires-Dist: pyperclip (~=1.8)
Requires-Dist: pygments (~=2.6)
Provides-Extra: dev
Requires-Dist: pytest ; extra == 'dev'
Requires-Dist: coverage[toml] (>=5.0.2) ; extra == 'dev'
Requires-Dist: prospector[with_pyroma] ; extra == 'dev'
Requires-Dist: black ; extra == 'dev'
Requires-Dist: twine ; extra == 'dev'
Requires-Dist: wheel ; extra == 'dev'
Provides-Extra: tests
Requires-Dist: pytest ; extra == 'tests'
Requires-Dist: coverage[toml] (>=5.0.2) ; extra == 'tests'
